rw_calibration/__init__.py
rw_calibration/__main__.py
rw_calibration/cli.py
rw_calibration/rw_calibration.py
rw_calibration-0.3.0.dist-info/AUTHORS.rst
rw_calibration-0.3.0.dist-info/LICENSE
rw_calibration-0.3.0.dist-info/METADATA
rw_calibration-0.3.0.dist-info/WHEEL
rw_calibration-0.3.0.dist-info/entry_points.txt
rw_calibration-0.3.0.dist-info/top_level.txt
rw_calibration-0.3.0.dist-info/RECORD
