Metadata-Version: 2.1
Name: rw-calibration
Version: 0.3.0
Summary: A Utility to perform Robot to World Calibration
Home-page: https://github.com/mrossi93/rw_calibration
Author: Matteo Rossi
Author-email: rossimatteo1993@gmail.com
License: MIT license
Keywords: rw_calibration
Platform: UNKNOWN
Classifier: Development Status :: 3 - Alpha
Classifier: Intended Audience :: Developers
Classifier: License :: OSI Approved :: MIT License
Classifier: Natural Language :: English
Classifier: Programming Language :: Python :: 3
Classifier: Programming Language :: Python :: 3.6
Classifier: Programming Language :: Python :: 3.7
Classifier: Programming Language :: Python :: 3.8
Requires-Python: >=3.6
Requires-Dist: Click (>=7.0)
Requires-Dist: Numpy
Requires-Dist: colorama
